homeservices/__init__.py
homeservices/config-template.yml
homeservices/wsgi.py
homeservices/webservice/__init__.py
homeservices/webservice/db_connector.py
homeservices/webservice/debugger.py
homeservices/webservice/webservice.py
tests/__init__.py
tests/test_000.py
tests/data/config-template.yml
homeservices-0.2.5.dist-info/METADATA
homeservices-0.2.5.dist-info/WHEEL
homeservices-0.2.5.dist-info/top_level.txt
homeservices-0.2.5.dist-info/RECORD
